{
	"success": true,
	"response":[
		{
			"date" : 29,
			"month" : "Aug",
			"title": "Thursday Roundup # 40",
			"description" : "This is our web design and development news series where we share our favorite design/development related articles, resources, tutorials and awesome freebies. "
		},
		{
			"date" : 15,
			"month" : "Jun",
			"title": "Retina Ready Responsive App Landing Page Website Template",
			"description" : "App Landing is a retina ready responsive app landing page website template perfect for software and application developers and small business owners looking to promote their iPhone, iPad, Android Apps and software products."
		}
	]
}